{"_path":"/user-guides/livemap","_dir":"user-guides","_draft":false,"_partial":false,"_locale":"","title":"Livemap","description":"","body":{"type":"root","children":[{"type":"element","tag":"p","props":{},"children":[{"type":"element","tag":"img","props":{"alt":"Feature Livemapo","src":"/images/screenshots/features-livemap.png"},"children":[]}]},{"type":"element","tag":"h2","props":{"id":"features"},"children":[{"type":"text","value":"Features"}]},{"type":"element","tag":"ul","props":{},"children":[{"type":"element","tag":"li","props":{},"children":[{"type":"text","value":"Live position of your colleagues (depending on what your faction is allowed to see)."}]},{"type":"element","tag":"li","props":{},"children":[{"type":"text","value":"Markers on the map of different types:\n"},{"type":"element","tag":"ul","props":{},"children":[{"type":"element","tag":"li","props":{},"children":[{"type":"text","value":"Dots"}]},{"type":"element","tag":"li","props":{},"children":[{"type":"text","value":"Circles"}]},{"type":"element","tag":"li","props":{},"children":[{"type":"text","value":"Icons - A list of the available icons can be found "},{"type":"element","tag":"a","props":{"href":"https://github.com/fivenet-app/fivenet/blob/main/src/components/livemap/helpers.ts#L90","rel":["nofollow"]},"children":[{"type":"text","value":"in the code here"}]},{"type":"text","value":"."}]}]}]}]}],"toc":{"title":"","searchDepth":2,"depth":2,"links":[{"id":"features","depth":2,"text":"Features"}]}},"_type":"markdown","_id":"content:2.user-guides:5.livemap.md","_source":"content","_file":"2.user-guides/5.livemap.md","_stem":"2.user-guides/5.livemap","_extension":"md"}